symdyn/__init__.py
symdyn/algebra.py
symdyn/types.py
symdyn/utils.py
symdyn/sun/__init__.py
symdyn/sun/utils.py
symdyn-0.1.0.dist-info/licenses/LICENCE
symdyn-0.1.0.dist-info/METADATA
symdyn-0.1.0.dist-info/WHEEL
symdyn-0.1.0.dist-info/top_level.txt
symdyn-0.1.0.dist-info/RECORD
